{
      "status": "success",
      "data": {
            "resultType": "matrix",
            "result": [
                  {
                        "metric": {
                              "__name__": "alert_endpoint_call",
                              "exported_instance": "alertapi:5001",
                              "exported_job": "alertapi",
                              "instance": "pushgateway:9091",
                              "job": "pushgateway"
                        },
                        "values": [
                              [
                                    1713210099,
                                    "1"
                              ],
                              [
                                    1713210104,
                                    "1"
                              ],
                              [
                                    1713210109,
                                    "1"
                              ],
                              [
                                    1713210114,
                                    "1"
                              ],
                              [
                                    1713210119,
                                    "1"
                              ],
                              [
                                    1713210124,
                                    "1"
                              ],
                              [
                                    1713210129,
                                    "1"
                              ],
                              [
                                    1713210134,
                                    "1"
                              ],
                              [
                                    1713210139,
                                    "1"
                              ],
                              [
                                    1713210144,
                                    "1"
                              ],
                              [
                                    1713210149,
                                    "1"
                              ],
                              [
                                    1713210154,
                                    "1"
                              ],
                              [
                                    1713210159,
                                    "1"
                              ],
                              [
                                    1713210164,
                                    "1"
                              ],
                              [
                                    1713210169,
                                    "1"
                              ],
                              [
                                    1713210174,
                                    "1"
                              ],
                              [
                                    1713210179,
                                    "1"
                              ],
                              [
                                    1713210184,
                                    "1"
                              ],
                              [
                                    1713210189,
                                    "1"
                              ],
                              [
                                    1713210194,
                                    "1"
                              ],
                              [
                                    1713210199,
                                    "1"
                              ],
                              [
                                    1713210204,
                                    "1"
                              ]
                        ]
                  }
            ]
      }
}