{
      "status": "success",
      "data": {
            "resultType": "matrix",
            "result": [
                  {
                        "metric": {
                              "testid": "threadloadtest"
                        },
                        "values": [
                              [
                                    1713220786,
                                    "8"
                              ],
                              [
                                    1713220791,
                                    "69"
                              ],
                              [
                                    1713220796,
                                    "82"
                              ],
                              [
                                    1713220801,
                                    "82"
                              ],
                              [
                                    1713220806,
                                    "178"
                              ],
                              [
                                    1713220811,
                                    "178"
                              ],
                              [
                                    1713220816,
                                    "219"
                              ],
                              [
                                    1713220821,
                                    "278"
                              ],
                              [
                                    1713220826,
                                    "418"
                              ],
                              [
                                    1713220831,
                                    "464"
                              ],
                              [
                                    1713220836,
                                    "493"
                              ],
                              [
                                    1713220841,
                                    "561"
                              ],
                              [
                                    1713220846,
                                    "576"
                              ],
                              [
                                    1713220851,
                                    "692"
                              ],
                              [
                                    1713220856,
                                    "692"
                              ],
                              [
                                    1713220861,
                                    "725"
                              ],
                              [
                                    1713220866,
                                    "758"
                              ],
                              [
                                    1713220871,
                                    "785"
                              ],
                              [
                                    1713220876,
                                    "811"
                              ],
                              [
                                    1713220881,
                                    "844"
                              ],
                              [
                                    1713220886,
                                    "940"
                              ],
                              [
                                    1713220891,
                                    "1035"
                              ],
                              [
                                    1713220896,
                                    "1129"
                              ],
                              [
                                    1713220901,
                                    "1357"
                              ],
                              [
                                    1713220906,
                                    "1462"
                              ],
                              [
                                    1713220911,
                                    "1545"
                              ],
                              [
                                    1713220916,
                                    "1812"
                              ],
                              [
                                    1713220921,
                                    "2334"
                              ],
                              [
                                    1713220926,
                                    "2394"
                              ]
                        ]
                  }
            ]
      }
}