{
      "status": "success",
      "data": {
            "resultType": "matrix",
            "result": [
                  {
                        "metric": {
                              "__name__": "system_runtime_threadpool_queue_length",
                              "exported_instance": "webserver:5000",
                              "exported_job": "webserver",
                              "instance": "pushgateway:9091",
                              "job": "pushgateway"
                        },
                        "values": [
                              [
                                    1713175892,
                                    "5"
                              ],
                              [
                                    1713175897,
                                    "2"
                              ],
                              [
                                    1713175902,
                                    "1"
                              ],
                              [
                                    1713175907,
                                    "13"
                              ],
                              [
                                    1713175912,
                                    "13"
                              ],
                              [
                                    1713175917,
                                    "0"
                              ],
                              [
                                    1713175922,
                                    "14"
                              ],
                              [
                                    1713175927,
                                    "51"
                              ],
                              [
                                    1713175932,
                                    "35"
                              ],
                              [
                                    1713175937,
                                    "0"
                              ],
                              [
                                    1713175942,
                                    "45"
                              ],
                              [
                                    1713175947,
                                    "22"
                              ],
                              [
                                    1713175952,
                                    "3"
                              ],
                              [
                                    1713175957,
                                    "12"
                              ],
                              [
                                    1713175962,
                                    "2"
                              ],
                              [
                                    1713175967,
                                    "3"
                              ],
                              [
                                    1713175972,
                                    "0"
                              ],
                              [
                                    1713175977,
                                    "9"
                              ],
                              [
                                    1713175982,
                                    "0"
                              ],
                              [
                                    1713175987,
                                    "17"
                              ],
                              [
                                    1713175992,
                                    "0"
                              ],
                              [
                                    1713175997,
                                    "36"
                              ],
                              [
                                    1713176002,
                                    "3"
                              ],
                              [
                                    1713176007,
                                    "15"
                              ],
                              [
                                    1713176012,
                                    "0"
                              ],
                              [
                                    1713176017,
                                    "16"
                              ],
                              [
                                    1713176022,
                                    "7"
                              ],
                              [
                                    1713176027,
                                    "0"
                              ],
                              [
                                    1713176032,
                                    "0"
                              ],
                              [
                                    1713176037,
                                    "0"
                              ]
                        ]
                  }
            ]
      }
}