{
      "status": "success",
      "data": {
            "resultType": "matrix",
            "result": [
                  {
                        "metric": {
                              "testid": "threadloadtest"
                        },
                        "values": [
                              [
                                    1713196611,
                                    "9.858080726896292"
                              ],
                              [
                                    1713196616,
                                    "9.316258155346837"
                              ],
                              [
                                    1713196621,
                                    "7.651416981459617"
                              ],
                              [
                                    1713196626,
                                    "8.605108841247723"
                              ],
                              [
                                    1713196631,
                                    "5.581734884550245"
                              ],
                              [
                                    1713196636,
                                    "9.77197477517766"
                              ],
                              [
                                    1713196641,
                                    "10.295785981465999"
                              ],
                              [
                                    1713196646,
                                    "11.492904667233546"
                              ],
                              [
                                    1713196651,
                                    "12.691294349515559"
                              ],
                              [
                                    1713196656,
                                    "12.047559473717877"
                              ],
                              [
                                    1713196661,
                                    "13.063513029780854"
                              ],
                              [
                                    1713196666,
                                    "19.74486343769882"
                              ],
                              [
                                    1713196671,
                                    "20.232797164104383"
                              ],
                              [
                                    1713196676,
                                    "4.735927414339421"
                              ],
                              [
                                    1713196681,
                                    "6.1828015021417135"
                              ],
                              [
                                    1713196686,
                                    "6.149267249638198"
                              ],
                              [
                                    1713196691,
                                    "6.652727585976653"
                              ],
                              [
                                    1713196696,
                                    "6.966032185137333"
                              ],
                              [
                                    1713196701,
                                    "8.546063320413719"
                              ],
                              [
                                    1713196706,
                                    "5.38857080327047"
                              ],
                              [
                                    1713196711,
                                    "7.693553390294169"
                              ],
                              [
                                    1713196716,
                                    "9.760015615216737"
                              ],
                              [
                                    1713196721,
                                    "9.691250445441446"
                              ],
                              [
                                    1713196726,
                                    "9.852699104913876"
                              ],
                              [
                                    1713196731,
                                    "9.773768649171798"
                              ],
                              [
                                    1713196736,
                                    "2.5321748580744257"
                              ],
                              [
                                    1713196741,
                                    "2.1719646920639897"
                              ],
                              [
                                    1713196746,
                                    "2.1719646920639897"
                              ]
                        ]
                  }
            ]
      }
}