{
      "status": "success",
      "data": {
            "resultType": "matrix",
            "result": [
                  {
                        "metric": {
                              "testid": "threadloadtest"
                        },
                        "values": [
                              [
                                    1713224180,
                                    "2"
                              ],
                              [
                                    1713224185,
                                    "4"
                              ],
                              [
                                    1713224190,
                                    "8"
                              ],
                              [
                                    1713224195,
                                    "57"
                              ],
                              [
                                    1713224200,
                                    "76"
                              ],
                              [
                                    1713224205,
                                    "171"
                              ],
                              [
                                    1713224210,
                                    "171"
                              ],
                              [
                                    1713224215,
                                    "199"
                              ],
                              [
                                    1713224220,
                                    "293"
                              ],
                              [
                                    1713224225,
                                    "339"
                              ],
                              [
                                    1713224230,
                                    "490"
                              ],
                              [
                                    1713224235,
                                    "532"
                              ],
                              [
                                    1713224240,
                                    "698"
                              ],
                              [
                                    1713224245,
                                    "718"
                              ],
                              [
                                    1713224250,
                                    "865"
                              ],
                              [
                                    1713224255,
                                    "989"
                              ],
                              [
                                    1713224260,
                                    "1066"
                              ],
                              [
                                    1713224265,
                                    "1268"
                              ],
                              [
                                    1713224270,
                                    "1413"
                              ],
                              [
                                    1713224275,
                                    "1506"
                              ],
                              [
                                    1713224280,
                                    "1641"
                              ],
                              [
                                    1713224285,
                                    "1883"
                              ],
                              [
                                    1713224290,
                                    "1982"
                              ],
                              [
                                    1713224295,
                                    "2132"
                              ],
                              [
                                    1713224300,
                                    "2408"
                              ],
                              [
                                    1713224305,
                                    "2544"
                              ],
                              [
                                    1713224310,
                                    "2683"
                              ],
                              [
                                    1713224315,
                                    "2787"
                              ],
                              [
                                    1713224320,
                                    "2860"
                              ],
                              [
                                    1713224325,
                                    "2919"
                              ]
                        ]
                  }
            ]
      }
}