{
      "status": "success",
      "data": {
            "resultType": "matrix",
            "result": [
                  {
                        "metric": {
                              "expected_response": "true",
                              "method": "GET",
                              "name": "http://threads.mahoney0101.com:5000/test-threadpool",
                              "proto": "HTTP/1.1",
                              "scenario": "ramp_up",
                              "status": "200",
                              "testid": "threadloadtest",
                              "url": "http://threads.mahoney0101.com:5000/test-threadpool"
                        },
                        "values": [
                              [
                                    1713163997,
                                    "3.112355528172413"
                              ],
                              [
                                    1713164002,
                                    "4.134218075560974"
                              ],
                              [
                                    1713164007,
                                    "4.956769549386362"
                              ],
                              [
                                    1713164012,
                                    "4.725237715078651"
                              ],
                              [
                                    1713164017,
                                    "6.429073565811877"
                              ],
                              [
                                    1713164022,
                                    "5.71184327158196"
                              ],
                              [
                                    1713164027,
                                    "5.429697162184773"
                              ],
                              [
                                    1713164032,
                                    "5.53272979239325"
                              ],
                              [
                                    1713164037,
                                    "4.573795093594279"
                              ],
                              [
                                    1713164042,
                                    "5.011896102393945"
                              ],
                              [
                                    1713164047,
                                    "4.659253040128326"
                              ],
                              [
                                    1713164052,
                                    "3.6834716190491132"
                              ],
                              [
                                    1713164057,
                                    "4.336169313284679"
                              ],
                              [
                                    1713164062,
                                    "5.8202084777908984"
                              ],
                              [
                                    1713164067,
                                    "4.4888160802852335"
                              ],
                              [
                                    1713164072,
                                    "3.637538316657781"
                              ],
                              [
                                    1713164077,
                                    "5.9025353562701115"
                              ],
                              [
                                    1713164082,
                                    "5.212216794068786"
                              ],
                              [
                                    1713164087,
                                    "3.8913412435049706"
                              ],
                              [
                                    1713164092,
                                    "5.206510162116387"
                              ],
                              [
                                    1713164097,
                                    "4.671565410038663"
                              ],
                              [
                                    1713164102,
                                    "3.865507679157543"
                              ],
                              [
                                    1713164107,
                                    "4.867328020922796"
                              ],
                              [
                                    1713164112,
                                    "4.716871681986385"
                              ],
                              [
                                    1713164117,
                                    "3.5517756026520715"
                              ],
                              [
                                    1713164122,
                                    "2.4434717587680956"
                              ],
                              [
                                    1713164127,
                                    "2.0392472572542926"
                              ],
                              [
                                    1713164132,
                                    "2.029159324606071"
                              ]
                        ]
                  }
            ]
      }
}