{
      "status": "success",
      "data": {
            "resultType": "matrix",
            "result": [
                  {
                        "metric": {
                              "__name__": "busy_worker_threads",
                              "exported_instance": "webserver:5000",
                              "exported_job": "webserver",
                              "instance": "pushgateway:9091",
                              "job": "pushgateway"
                        },
                        "values": [
                              [
                                    1713205691,
                                    "11"
                              ],
                              [
                                    1713205696,
                                    "6"
                              ],
                              [
                                    1713205701,
                                    "8"
                              ],
                              [
                                    1713205706,
                                    "11"
                              ],
                              [
                                    1713205711,
                                    "13"
                              ],
                              [
                                    1713205716,
                                    "34"
                              ],
                              [
                                    1713205721,
                                    "17"
                              ],
                              [
                                    1713205726,
                                    "18"
                              ],
                              [
                                    1713205731,
                                    "37"
                              ],
                              [
                                    1713205736,
                                    "3"
                              ],
                              [
                                    1713205741,
                                    "24"
                              ],
                              [
                                    1713205746,
                                    "47"
                              ],
                              [
                                    1713205751,
                                    "48"
                              ],
                              [
                                    1713205756,
                                    "10"
                              ],
                              [
                                    1713205761,
                                    "51"
                              ],
                              [
                                    1713205766,
                                    "51"
                              ],
                              [
                                    1713205771,
                                    "34"
                              ],
                              [
                                    1713205776,
                                    "17"
                              ],
                              [
                                    1713205781,
                                    "36"
                              ],
                              [
                                    1713205786,
                                    "36"
                              ],
                              [
                                    1713205791,
                                    "57"
                              ],
                              [
                                    1713205796,
                                    "31"
                              ],
                              [
                                    1713205801,
                                    "38"
                              ],
                              [
                                    1713205806,
                                    "38"
                              ],
                              [
                                    1713205811,
                                    "37"
                              ],
                              [
                                    1713205816,
                                    "55"
                              ],
                              [
                                    1713205821,
                                    "30"
                              ],
                              [
                                    1713205826,
                                    "19"
                              ],
                              [
                                    1713205831,
                                    "18"
                              ],
                              [
                                    1713205836,
                                    "2"
                              ]
                        ]
                  },
                  {
                        "metric": {
                              "__name__": "busy_worker_threads",
                              "instance": "webserver:5000",
                              "job": "webserver"
                        },
                        "values": [
                              [
                                    1713205681,
                                    "0"
                              ],
                              [
                                    1713205686,
                                    "0"
                              ],
                              [
                                    1713205691,
                                    "4"
                              ],
                              [
                                    1713205696,
                                    "4"
                              ],
                              [
                                    1713205701,
                                    "8"
                              ],
                              [
                                    1713205706,
                                    "8"
                              ],
                              [
                                    1713205711,
                                    "13"
                              ],
                              [
                                    1713205716,
                                    "13"
                              ],
                              [
                                    1713205721,
                                    "35"
                              ],
                              [
                                    1713205726,
                                    "35"
                              ],
                              [
                                    1713205731,
                                    "39"
                              ],
                              [
                                    1713205736,
                                    "39"
                              ],
                              [
                                    1713205741,
                                    "22"
                              ],
                              [
                                    1713205746,
                                    "22"
                              ],
                              [
                                    1713205751,
                                    "48"
                              ],
                              [
                                    1713205756,
                                    "48"
                              ],
                              [
                                    1713205761,
                                    "31"
                              ],
                              [
                                    1713205766,
                                    "31"
                              ],
                              [
                                    1713205771,
                                    "32"
                              ],
                              [
                                    1713205776,
                                    "32"
                              ],
                              [
                                    1713205781,
                                    "55"
                              ],
                              [
                                    1713205786,
                                    "55"
                              ],
                              [
                                    1713205791,
                                    "57"
                              ],
                              [
                                    1713205796,
                                    "57"
                              ],
                              [
                                    1713205801,
                                    "38"
                              ],
                              [
                                    1713205806,
                                    "38"
                              ],
                              [
                                    1713205811,
                                    "58"
                              ],
                              [
                                    1713205816,
                                    "58"
                              ],
                              [
                                    1713205821,
                                    "50"
                              ],
                              [
                                    1713205826,
                                    "50"
                              ],
                              [
                                    1713205831,
                                    "14"
                              ],
                              [
                                    1713205836,
                                    "14"
                              ]
                        ]
                  }
            ]
      }
}