{
      "status": "success",
      "data": {
            "resultType": "matrix",
            "result": [
                  {
                        "metric": {
                              "testid": "threadloadtest"
                        },
                        "values": [
                              [
                                    1713217120,
                                    "4.697608830608407"
                              ],
                              [
                                    1713217125,
                                    "6.392174509790946"
                              ],
                              [
                                    1713217130,
                                    "9.68586882345903"
                              ],
                              [
                                    1713217135,
                                    "9.82937874299008"
                              ],
                              [
                                    1713217140,
                                    "10.035674252315967"
                              ],
                              [
                                    1713217145,
                                    "14.306748077110145"
                              ],
                              [
                                    1713217150,
                                    "10.35318994927842"
                              ],
                              [
                                    1713217155,
                                    "10.222074068252322"
                              ],
                              [
                                    1713217160,
                                    "18.145599357828853"
                              ],
                              [
                                    1713217165,
                                    "18.78436151428978"
                              ],
                              [
                                    1713217170,
                                    "17.65116245202404"
                              ],
                              [
                                    1713217175,
                                    "3.114664418587434"
                              ],
                              [
                                    1713217180,
                                    "2.517798239349976"
                              ],
                              [
                                    1713217185,
                                    "4.016090263584933"
                              ],
                              [
                                    1713217190,
                                    "5.571837400655842"
                              ],
                              [
                                    1713217195,
                                    "5.6483488866139675"
                              ],
                              [
                                    1713217200,
                                    "5.57469244408692"
                              ],
                              [
                                    1713217205,
                                    "5.715034823599128"
                              ],
                              [
                                    1713217210,
                                    "9.810244087052606"
                              ],
                              [
                                    1713217215,
                                    "9.811113844140678"
                              ],
                              [
                                    1713217220,
                                    "9.714570807365236"
                              ],
                              [
                                    1713217225,
                                    "11.862268197705529"
                              ],
                              [
                                    1713217230,
                                    "23.006288896552658"
                              ],
                              [
                                    1713217235,
                                    "24.742372568974766"
                              ],
                              [
                                    1713217240,
                                    "34.355106475247545"
                              ],
                              [
                                    1713217245,
                                    "34.56712841741457"
                              ],
                              [
                                    1713217250,
                                    "3.089074384319197"
                              ],
                              [
                                    1713217255,
                                    "2.1719646920639897"
                              ]
                        ]
                  }
            ]
      }
}