{
      "status": "success",
      "data": {
            "resultType": "matrix",
            "result": [
                  {
                        "metric": {
                              "testid": "threadloadtest"
                        },
                        "values": [
                              [
                                    1713311063,
                                    "6.386591229586971"
                              ],
                              [
                                    1713311068,
                                    "6.386591229586963"
                              ],
                              [
                                    1713311073,
                                    "8.662516603109687"
                              ],
                              [
                                    1713311078,
                                    "9.368371429221021"
                              ],
                              [
                                    1713311083,
                                    "9.279936782646656"
                              ],
                              [
                                    1713311088,
                                    "5.836050417741164"
                              ],
                              [
                                    1713311093,
                                    "5.95892779025461"
                              ],
                              [
                                    1713311098,
                                    "4.626545275325429"
                              ],
                              [
                                    1713311103,
                                    "6.0905821179476005"
                              ],
                              [
                                    1713311108,
                                    "6.590380957032216"
                              ],
                              [
                                    1713311113,
                                    "6.579214396624259"
                              ],
                              [
                                    1713311118,
                                    "6.617739030031717"
                              ],
                              [
                                    1713311123,
                                    "9.300466254172841"
                              ],
                              [
                                    1713311128,
                                    "10.553124928945628"
                              ],
                              [
                                    1713311133,
                                    "11.197899478032314"
                              ],
                              [
                                    1713311138,
                                    "10.48739548462129"
                              ],
                              [
                                    1713311143,
                                    "9.076747654207928"
                              ],
                              [
                                    1713311148,
                                    "15.123562696241342"
                              ],
                              [
                                    1713311153,
                                    "15.843967601224787"
                              ],
                              [
                                    1713311158,
                                    "19.951517721823507"
                              ],
                              [
                                    1713311163,
                                    "25.792029247322958"
                              ],
                              [
                                    1713311168,
                                    "25.7250298848752"
                              ],
                              [
                                    1713311173,
                                    "38.175176012493296"
                              ],
                              [
                                    1713311178,
                                    "41.309432655051324"
                              ],
                              [
                                    1713311183,
                                    "44.80411780628622"
                              ],
                              [
                                    1713311188,
                                    "45.67125175834576"
                              ],
                              [
                                    1713311193,
                                    "46.2173734139609"
                              ],
                              [
                                    1713311198,
                                    "2.6734934345530386"
                              ]
                        ]
                  }
            ]
      }
}