{
      "status": "success",
      "data": {
            "resultType": "matrix",
            "result": [
                  {
                        "metric": {},
                        "values": [
                              [
                                    1713224387,
                                    "2.0000000000436557"
                              ],
                              [
                                    1713224392,
                                    "10.000000000218279"
                              ],
                              [
                                    1713224397,
                                    "2.0000000000436557"
                              ],
                              [
                                    1713224402,
                                    "3.0000000002473826"
                              ],
                              [
                                    1713224407,
                                    "2.9999999998835847"
                              ],
                              [
                                    1713224412,
                                    "45.99999999991269"
                              ],
                              [
                                    1713224417,
                                    "6.999999999970896"
                              ],
                              [
                                    1713224422,
                                    "0.9999999998399289"
                              ],
                              [
                                    1713224427,
                                    "10.000000000218279"
                              ],
                              [
                                    1713224432,
                                    "18.999999999869033"
                              ],
                              [
                                    1713224437,
                                    "6.000000000130967"
                              ],
                              [
                                    1713224442,
                                    "0.9999999998399289"
                              ],
                              [
                                    1713224447,
                                    "6.000000000130967"
                              ],
                              [
                                    1713224452,
                                    "2.0000000000436557"
                              ],
                              [
                                    1713224457,
                                    "7.999999999810825"
                              ],
                              [
                                    1713224462,
                                    "5.999999999767169"
                              ],
                              [
                                    1713224467,
                                    "10.000000000218279"
                              ],
                              [
                                    1713224472,
                                    "3.0000000002473826"
                              ],
                              [
                                    1713224477,
                                    "9.99999999985448"
                              ],
                              [
                                    1713224482,
                                    "13.000000000101863"
                              ],
                              [
                                    1713224487,
                                    "4.99999999992724"
                              ],
                              [
                                    1713224492,
                                    "13.000000000101863"
                              ],
                              [
                                    1713224497,
                                    "9.000000000014552"
                              ],
                              [
                                    1713224502,
                                    "13.000000000101863"
                              ],
                              [
                                    1713224507,
                                    "6.999999999970896"
                              ],
                              [
                                    1713224512,
                                    "2.9999999998835847"
                              ],
                              [
                                    1713224517,
                                    "6.000000000130967"
                              ],
                              [
                                    1713224522,
                                    "11.000000000058208"
                              ],
                              [
                                    1713224527,
                                    "6.999999999970896"
                              ],
                              [
                                    1713224532,
                                    "7.999999999810825"
                              ],
                              [
                                    1713224537,
                                    "6.999999999970896"
                              ],
                              [
                                    1713224542,
                                    "5.999999999767169"
                              ],
                              [
                                    1713224547,
                                    "2.9999999998835847"
                              ]
                        ]
                  }
            ]
      }
}